flash_attn3_jax/varlen_fwd.py
flash_attn3_jax/varlen.py
flash_attn3_jax/varlen_bwd.py
flash_attn3_jax/flash_hlo.py
flash_attn3_jax/flash_sharding.py
flash_attn3_jax/flash.py
flash_attn3_jax/ring_attention.py
flash_attn3_jax/kvcache.py
flash_attn3_jax/__init__.py
flash_attn3_jax_lib/flash_api.cpython-311-x86_64-linux-gnu.so
flash_attn3_jax.libs/libcudart-8774224f.so.12.4.127
flash_attn3_jax-0.2.2.dist-info/WHEEL
flash_attn3_jax-0.2.2.dist-info/METADATA
flash_attn3_jax-0.2.2.dist-info/RECORD
flash_attn3_jax-0.2.2.dist-info/licenses/LICENSE
