Metadata-Version: 2.2
Name: flash-attn3-jax
Version: 0.2.2
Summary: FlashAttention-3 JAX binding using XLA FFI
Author-Email: Romain Fabre <romain@kyutai.org>
License: BSD-3-Clause
Classifier: Programming Language :: Python :: 3
Classifier: License :: OSI Approved :: BSD License
Classifier: Operating System :: Unix
Project-URL: Repository, https://github.com/kyutai-labs/flash-attn3-jax
Requires-Python: >=3.11
Requires-Dist: jax<=0.7.0,>=0.5.0
Requires-Dist: einops
